openai_unofficial/__init__.py
openai_unofficial/main.py
openai_unofficial-0.1.2.dist-info/METADATA
openai_unofficial-0.1.2.dist-info/WHEEL
openai_unofficial-0.1.2.dist-info/licenses/LICENCE
openai_unofficial-0.1.2.dist-info/RECORD
