Metadata-Version: 2.3
Name: openai-unofficial
Version: 0.1.2
Summary: Free & Unlimited Unofficial OpenAI API Python SDK - Supports all OpenAI Models & Endpoints
Project-URL: Homepage, https://github.com/SreejanPersonal/openai-unofficial
Project-URL: Bug Tracker, https://github.com/SreejanPersonal/openai-unofficial/issues
Project-URL: Youtube, https://www.youtube.com/@DevsDoCode
Project-URL: Instragram, https://www.instagram.com/sree.shades_/
Project-URL: LinkedIn, https://www.linkedin.com/in/developer-sreejan/
Project-URL: Twitter, https://twitter.com/Anand_Sreejan
Author-email: DevsDoCode <devsdocode@gmail.com>
License: MIT
License-File: LICENCE
Keywords: ai,api,chatgpt,dall-e,gpt,machine-learning,openai,text-to-speech,tts
Classifier: Development Status :: 4 - Beta
Classifier: Intended Audience :: Developers
Classifier: License :: OSI Approved :: MIT License
Classifier: Operating System :: OS Independent
Classifier: Programming Language :: Python :: 3
Classifier: Programming Language :: Python :: 3.7
Classifier: Programming Language :: Python :: 3.8
Classifier: Programming Language :: Python :: 3.9
Classifier: Programming Language :: Python :: 3.10
Classifier: Programming Language :: Python :: 3.11
Classifier: Topic :: Scientific/Engineering :: Artificial Intelligence
Classifier: Topic :: Software Development :: Libraries :: Python Modules
Requires-Python: >=3.7
Requires-Dist: requests>=2.28.0
